{
	"configurations" : 
	[
		{
			"directories" : 
			[
				{
					"build" : ".",
					"jsonFile" : "directory-.-Release-f5ebdc15457944623624.json",
					"minimumCMakeVersion" : 
					{
						"string" : "3.27"
					},
					"projectIndex" : 0,
					"source" : ".",
					"targetIndexes" : 
					[
						0
					]
				}
			],
			"name" : "Release",
			"projects" : 
			[
				{
					"directoryIndexes" : 
					[
						0
					],
					"name" : "wejsciowka_03",
					"targetIndexes" : 
					[
						0
					]
				}
			],
			"targets" : 
			[
				{
					"directoryIndex" : 0,
					"id" : "wejsciowka_03::@6890427a1f51a3e7e1df",
					"jsonFile" : "target-wejsciowka_03-Release-8a530b6755a0b7304a7b.json",
					"name" : "wejsciowka_03",
					"projectIndex" : 0
				}
			]
		}
	],
	"kind" : "codemodel",
	"paths" : 
	{
		"build" : "/Users/oliwer/Library/CloudStorage/OneDrive-Osobisty/Dokumenty/Studia/Podstawy programowania (L)/wejsciowka_03/cmake-build-release",
		"source" : "/Users/oliwer/Library/CloudStorage/OneDrive-Osobisty/Dokumenty/Studia/Podstawy programowania (L)/wejsciowka_03"
	},
	"version" : 
	{
		"major" : 2,
		"minor" : 6
	}
}
